servicex_cli/__init__.py
servicex_cli/servicex.py
servicex_cli-1.0.1.dist-info/LICENSE
servicex_cli-1.0.1.dist-info/METADATA
servicex_cli-1.0.1.dist-info/WHEEL
servicex_cli-1.0.1.dist-info/entry_points.txt
servicex_cli-1.0.1.dist-info/top_level.txt
servicex_cli-1.0.1.dist-info/RECORD
