Metadata-Version: 2.1
Name: servicex-cli
Version: 1.0.1
Summary: CLI for the ServiceX Data Server
Home-page: https://github.com/ssl-hep/servicex_cli
Author: Ben Galewsky (IRIS-HEP/NCSA/University of Illinois)
Author-email: bengal1@illinois.edu
Maintainer: Ben Galewsky (IRIS-HEP/NCSA/University of Illinois)
Maintainer-email: bengal1@illinois.edu
License: bsd 3 clause
Platform: Any
Classifier: Development Status :: 3 - Alpha
Classifier: Intended Audience :: Developers
Classifier: Intended Audience :: Information Technology
Classifier: Programming Language :: Python
Classifier: Topic :: Software Development
Classifier: Topic :: Utilities
Requires-Python: >=3.6
Requires-Dist: oauthlib (==3.1.0)
Requires-Dist: kubernetes
Requires-Dist: pyopenssl (==19.1.0)
Provides-Extra: test
Requires-Dist: flake8 (==3.5) ; extra == 'test'
Requires-Dist: pytest ; extra == 'test'
Requires-Dist: pytest-mock ; extra == 'test'
Requires-Dist: coverage (==4.5.2) ; extra == 'test'
Requires-Dist: codecov (==2.0.15) ; extra == 'test'
